{"title":"Chautauqua - Flat Irons","markdown":{"yaml":{"title":"Chautauqua - Flat Irons","date":"2023-01-14","categories":["hiking"],"image":"longmont.PNG"},"containsRefs":false,"markdown":"\n\nTechnically my first day of hiking in Colorado was at Chautauqua (Boulder) on the Flat Irons, but I apparently did not take any pictures except a car selfie, see thumbnail for this hike. The hike is recorded on GPS and on the maps post, and so I am leaving this entry brief to say, yes, I hiked! But also this list starts at 0 as in zero pictures from this wonderful day.\n\nI was joined by Nick, an old pal from way back when, and wish I'd gotten a shot of us to share. Guess this one's stuck in the old memory bank only.\n"},"formats":{"html":{"execute":{"fig-width":7,"fig-height":5,"fig-format":"retina","fig-dpi":96,"df-print":"default","error":false,"eval":true,"cache":null,"freeze":true,"echo":true,"output":true,"warning":true,"include":true,"keep-md":false,"keep-ipynb":false,"ipynb":null,"enabled":null,"daemon":null,"daemon-restart":false,"debug":false,"ipynb-filters":[],"engine":"markdown"},"render":{"keep-tex":false,"keep-source":false,"keep-hidden":false,"prefer-html":false,"output-divs":true,"output-ext":"html","fig-align":"default","fig-pos":null,"fig-env":null,"code-fold":"none","code-overflow":"scroll","code-link":false,"code-line-numbers":false,"code-tools":false,"tbl-colwidths":"auto","merge-includes":true,"latex-auto-mk":true,"latex-auto-install":true,"latex-clean":true,"latex-max-runs":10,"latex-makeindex":"makeindex","latex-makeindex-opts":[],"latex-tlmgr-opts":[],"latex-input-paths":[],"latex-output-dir":null,"link-external-icon":false,"link-external-newwindow":false,"self-contained-math":false,"format-resources":[]},"pandoc":{"standalone":true,"wrap":"none","default-image-extension":"png","to":"html","css":["../../styles.css"],"output-file":"my_day.html"},"language":{},"metadata":{"lang":"en","fig-responsive":true,"quarto-version":"1.2.313","editor":"visual","theme":"cosmo","title-block-banner":true,"title":"Chautauqua - Flat Irons","date":"2023-01-14","categories":["hiking"],"image":"longmont.PNG"},"extensions":{"book":{"multiFile":true}}}}}